LICENSE
recap/__init__.py
recap/config.py
recap/path_manager.py
recap-0.1.8.dist-info/LICENSE
recap-0.1.8.dist-info/METADATA
recap-0.1.8.dist-info/WHEEL
recap-0.1.8.dist-info/RECORD
