Metadata-Version: 2.1
Name: recap
Version: 0.1.8
Summary: Reproducible configurations for any project
Home-page: http://recap.readthedocs.io
License: Apache-2.0
Keywords: flake8,markdown,lint
Author: Georg Wölflein
Author-email: georgw7777@gmail.com
Requires-Python: >=3.9,<4.0
Classifier: Intended Audience :: Science/Research
Classifier: License :: OSI Approved :: Apache Software License
Classifier: Operating System :: OS Independent
Classifier: Programming Language :: Python :: 3
Classifier: Programming Language :: Python :: 3.9
Classifier: Programming Language :: Python :: 3.10
Classifier: Programming Language :: Python :: 3.11
Classifier: Topic :: Scientific/Engineering :: Artificial Intelligence
Provides-Extra: docs
Requires-Dist: m2r2 (>=0.3.3,<0.4.0) ; extra == "docs"
Requires-Dist: pyyaml (>=6.0.1,<7.0.0)
Requires-Dist: sphinx (<7) ; extra == "docs"
Requires-Dist: sphinx-rtd-theme (<2.0.0) ; extra == "docs"
Requires-Dist: wrapt (>=1.12.1,<2.0.0)
Requires-Dist: yacs (>=0.1.8,<0.2.0)
Project-URL: Repository, https://github.com/georg-wolflein/recap
